mactools/__init__.py
mactools/basemac.py
mactools/mac_common.py
mactools/macaddress.py
mactools/tools_common.py
mactools/update_ieee.py
mactools/version.py
mactools/oui_cache/__init__.py
mactools/oui_cache/oui_classes.py
mactools/oui_cache/oui_common.py
mactools/oui_cache/oui_core.py
mactools/resources/ieee/mam.csv
mactools/resources/ieee/oui.csv
mactools/resources/ieee/oui36.csv
mactools-1.8.0.dist-info/licenses/LICENSE
mactools-1.8.0.dist-info/METADATA
mactools-1.8.0.dist-info/WHEEL
mactools-1.8.0.dist-info/top_level.txt
mactools-1.8.0.dist-info/RECORD
