Metadata-Version: 2.4
Name: mactools
Version: 1.8.0
Summary: MAC Address-focused library similar to ipaddress
Author: Michael Buckley
License: MIT
Project-URL: Homepage, https://github.com/Michael-C-Buckley/mactools
Project-URL: Repository, https://github.com/Michael-C-Buckley/mactools
Project-URL: Issues, https://github.com/Michael-C-Buckley/mactools/issues
Keywords: python,networking,network,mac,oui,ieee
Classifier: Development Status :: 4 - Beta
Classifier: Intended Audience :: Developers
Classifier: License :: OSI Approved :: MIT License
Classifier: Programming Language :: Python :: 3
Classifier: Programming Language :: Python :: 3.10
Classifier: Programming Language :: Python :: 3.11
Classifier: Programming Language :: Python :: 3.12
Classifier: Programming Language :: Python :: 3.13
Classifier: Programming Language :: Python :: 3.14
Classifier: Topic :: Software Development :: Libraries :: Python Modules
Classifier: Topic :: System :: Networking
Requires-Python: >=3.8
License-File: LICENSE
Provides-Extra: dev
Requires-Dist: nox; extra == "dev"
Requires-Dist: coverage; extra == "dev"
Requires-Dist: black; extra == "dev"
Requires-Dist: isort; extra == "dev"
Requires-Dist: flake8; extra == "dev"
Dynamic: license-file
